cl/testlog/__init__.py
cl_testlog-0.0.1.dist-info/LICENSE
cl_testlog-0.0.1.dist-info/METADATA
cl_testlog-0.0.1.dist-info/WHEEL
cl_testlog-0.0.1.dist-info/top_level.txt
cl_testlog-0.0.1.dist-info/RECORD
