Metadata-Version: 2.1
Name: cl-testlog
Version: 0.0.1
Summary: CompatibL Platform Integration for Test Log
Home-page: https://github.com/compatibl/cl-testlog
Author: The Project Contributors
License: UNKNOWN
Project-URL: Source Code, https://github.com/compatibl/cl-testlog
Platform: UNKNOWN
Classifier: Development Status :: 3 - Alpha
Classifier: Intended Audience :: Developers
Classifier: Topic :: Software Development
Classifier: Topic :: Scientific/Engineering
Classifier: License :: OSI Approved :: Apache Software License
Classifier: Programming Language :: Python :: 3.9
Classifier: Programming Language :: Python :: 3.10
Classifier: Programming Language :: Python :: 3.11
Classifier: Operating System :: OS Independent
License-File: LICENSE
Requires-Dist: cl-runtime (>=2.0.2)
Requires-Dist: pdoc (>=12.0.2)
Requires-Dist: pytest (>=6.1.1)
Requires-Dist: testlog (>=0.0.1)
